openbb_terminal/SDK_README.md
openbb_terminal/__init__.py
openbb_terminal/alternative/__init__.py
openbb_terminal/alternative/alt_controller.py
openbb_terminal/alternative/covid/__init__.py
openbb_terminal/alternative/covid/countries.txt
openbb_terminal/alternative/covid/covid_controller.py
openbb_terminal/alternative/covid/covid_model.py
openbb_terminal/alternative/covid/covid_view.py
openbb_terminal/alternative/oss/github_model.py
openbb_terminal/alternative/oss/github_view.py
openbb_terminal/alternative/oss/oss_controller.py
openbb_terminal/alternative/oss/runa_model.py
openbb_terminal/alternative/oss/runa_view.py
openbb_terminal/base_helpers.py
openbb_terminal/common/__init__.py
openbb_terminal/common/behavioural_analysis/__init__.py
openbb_terminal/common/behavioural_analysis/finbrain_model.py
openbb_terminal/common/behavioural_analysis/finbrain_view.py
openbb_terminal/common/behavioural_analysis/finnhub_model.py
openbb_terminal/common/behavioural_analysis/finnhub_view.py
openbb_terminal/common/behavioural_analysis/google_model.py
openbb_terminal/common/behavioural_analysis/google_view.py
openbb_terminal/common/behavioural_analysis/reddit_helpers.py
openbb_terminal/common/behavioural_analysis/reddit_model.py
openbb_terminal/common/behavioural_analysis/reddit_view.py
openbb_terminal/common/behavioural_analysis/sentimentinvestor_model.py
openbb_terminal/common/behavioural_analysis/sentimentinvestor_view.py
openbb_terminal/common/behavioural_analysis/stocktwits_model.py
openbb_terminal/common/behavioural_analysis/stocktwits_view.py
openbb_terminal/common/behavioural_analysis/twitter_model.py
openbb_terminal/common/behavioural_analysis/twitter_view.py
openbb_terminal/common/common_model.py
openbb_terminal/common/feedparser_model.py
openbb_terminal/common/feedparser_view.py
openbb_terminal/common/newsapi_model.py
openbb_terminal/common/newsapi_view.py
openbb_terminal/common/quantitative_analysis/__init__.py
openbb_terminal/common/quantitative_analysis/qa_model.py
repl_openbb-2.1.7.dist-info/LICENSE
repl_openbb-2.1.7.dist-info/WHEEL
repl_openbb-2.1.7.dist-info/entry_points.txt
repl_openbb-2.1.7.dist-info/METADATA
repl_openbb-2.1.7.dist-info/RECORD
